swap_user/__init__.py
swap_user/admin.py
swap_user/apps.py
swap_user/base_forms.py
swap_user/base_senders.py
swap_user/helpers.py
swap_user/otp/__init__.py
swap_user/otp/forms.py
swap_user/otp/senders.py
swap_user/otp/services.py
swap_user/otp/sites.py
swap_user/otp/views.py
swap_user/settings.py
swap_user/tests/__init__.py
swap_user/tests/conftest.py
swap_user/tests/test_forms.py
swap_user/to_email/__init__.py
swap_user/to_email/admin.py
swap_user/to_email/apps.py
swap_user/to_email/base_managers.py
swap_user/to_email/base_models.py
swap_user/to_email/forms.py
swap_user/to_email/managers.py
swap_user/to_email/migrations/0001_initial.py
swap_user/to_email/migrations/0002_update_verbose_name.py
swap_user/to_email/migrations/__init__.py
swap_user/to_email/models.py
swap_user/to_email_otp/__init__.py
swap_user/to_email_otp/apps.py
swap_user/to_email_otp/base_managers.py
swap_user/to_email_otp/base_models.py
swap_user/to_email_otp/managers.py
swap_user/to_email_otp/migrations/0001_initial.py
swap_user/to_email_otp/migrations/__init__.py
swap_user/to_email_otp/models.py
swap_user/to_email_otp/templates/admin/check-otp.html
swap_user/to_email_otp/templates/admin/login-otp.html
swap_user/to_phone/__init__.py
swap_user/to_phone/admin.py
swap_user/to_phone/apps.py
swap_user/to_phone/base_managers.py
swap_user/to_phone/base_models.py
swap_user/to_phone/forms.py
swap_user/to_phone/managers.py
swap_user/to_phone/migrations/0001_initial.py
swap_user/to_phone/migrations/__init__.py
swap_user/to_phone/models.py
swap_user/to_phone_otp/__init__.py
swap_user/to_phone_otp/admin.py
swap_user/to_phone_otp/apps.py
swap_user/to_phone_otp/base_managers.py
swap_user/to_phone_otp/base_models.py
swap_user/to_phone_otp/forms.py
swap_user/to_phone_otp/managers.py
swap_user/to_phone_otp/migrations/0001_initial.py
swap_user/to_phone_otp/migrations/__init__.py
swap_user/to_phone_otp/models.py
django_swap_user-0.9.8.dist-info/LICENSE
django_swap_user-0.9.8.dist-info/WHEEL
django_swap_user-0.9.8.dist-info/METADATA
django_swap_user-0.9.8.dist-info/RECORD
