Metadata-Version: 2.1
Name: django-swap-user
Version: 0.9.8
Summary: (Beta) Simple and flexible way to swap default Django User
Home-page: http://github.com/artinnok/django-swap-user
License: MIT
Keywords: django,swap,user,custom,user,auth,model,email,username,phone,mixins,authentication
Author: Artem Innokentiev
Author-email: artinnok@protonmail.com
Maintainer: Artem Innokentiev
Maintainer-email: artinnok@protonmail.com
Requires-Python: >=3.6,<4.0
Classifier: License :: OSI Approved :: MIT License
Classifier: Programming Language :: Python :: 3
Classifier: Programming Language :: Python :: 3.10
Classifier: Programming Language :: Python :: 3.6
Classifier: Programming Language :: Python :: 3.7
Classifier: Programming Language :: Python :: 3.8
Classifier: Programming Language :: Python :: 3.9
Requires-Dist: django (>=2.2)
Requires-Dist: django-phonenumber-field[phonenumbers] (>=5.2.0,<6.0.0)
Project-URL: Repository, http://github.com/artinnok/django-swap-user
